{"name": "test_logout", "status": "passed", "description": "Logout", "start": 1659631941099, "stop": 1659631941800, "uuid": "347873c0-5a0a-435c-b4a5-8686710f9fe6", "historyId": "08ee303d633e7df0e4be7ef4815d61b7", "testCaseId": "a7f171cd253ece7ce3ead18e572623e9", "fullName": "petstore_api_test#test_logout", "labels": [{"name": "suite", "value": "petstore_api_test"}, {"name": "host", "value": "LAPTOP-H50IM0SD"}, {"name": "thread", "value": "8704-MainThread"}, {"name": "framework", "value": "pytest"}, {"name": "language", "value": "cpython3"}, {"name": "package", "value": "petstore_api_test"}]}